{
    "url": "https://xn--80aeal8bmm8fsa.xn--p1ai/wp-content/uploads/2019/02/7-25.jpg",
    "key": "000028081",
    "status": "success",
    "error_message": null,
    "width": 512,
    "height": 512,
    "original_width": 800,
    "original_height": 600,
    "exif": "{\"Image Orientation\": \"Horizontal (normal)\", \"Image XResolution\": \"72\", \"Image YResolution\": \"72\", \"Image ResolutionUnit\": \"Pixels/Inch\", \"Image Software\": \"ACDSee Pro 9\", \"Image DateTime\": \"2019:02:10 17:51:08\", \"Image YCbCrPositioning\": \"Centered\", \"Image ExifOffset\": \"159\", \"EXIF SubSecTime\": \"273\", \"EXIF ExifImageWidth\": \"800\", \"EXIF ExifImageLength\": \"600\"}",
    "sha256": "5c6de100dba71faa79da302656e0aa32607f538d55c81cc1ce1ee9043a637a5a"
}