{
    "url": "https://thumbs.dreamstime.com/t/%E5%85%B3%E9%97%AD%E5%B7%A8%E5%A4%A7%E7%9A%84%E5%9C%A8%E6%97%A5%E8%90%BD%E5%A4%A9%E7%A9%BA%EF%BC%8C-hendaye%E7%9A%84%E5%B3%AD%E5%A3%81%E5%B2%A9%E7%9F%B3%E8%A2%AB%E8%85%90%E8%9A%80%E7%9A%84%E7%BA%B9%E7%90%86-112953769.jpg",
    "key": "000023717",
    "status": "success",
    "error_message": null,
    "width": 512,
    "height": 512,
    "original_width": 240,
    "original_height": 160,
    "exif": "{}",
    "sha256": "dd35070873d37e91fd2d77f06f60c75dad2500cecf365a0787218954456b9240"
}