{
    "url": "https://thumbs.dreamstime.com/t/salad-10968442.jpg",
    "key": "000024265",
    "status": "success",
    "error_message": null,
    "width": 512,
    "height": 512,
    "original_width": 205,
    "original_height": 160,
    "exif": "{\"Image XResolution\": \"300\", \"Image YResolution\": \"300\", \"Image ResolutionUnit\": \"Pixels/Inch\", \"Image YCbCrPositioning\": \"Centered\", \"Image Copyright\": \"(c) Alexeys | Dreamstime.com\", \"Image XPTitle\": \"[0, 0, 0, 0, 0, 0, 0, 0, 0, 0, 0, 0, 0, 0, 0, 0, 0, 0, 0, 0, ... ]\"}",
    "sha256": "bcaa62b27100886f9518826dc1cc1b6a802b6c233688d29ce72b1bb45746c183"
}