{
    "url": "https://tabi.kaigai55.com/wp-content/uploads/2020/02/3CEEA4D9-2DB6-41F3-81C6-A331543F9D23-600x450.jpeg",
    "key": "000022151",
    "status": "success",
    "error_message": null,
    "width": 512,
    "height": 512,
    "original_width": 600,
    "original_height": 450,
    "exif": "{\"Image Orientation\": \"Horizontal (normal)\", \"Image XResolution\": \"72\", \"Image YResolution\": \"72\", \"Image ResolutionUnit\": \"Pixels/Inch\", \"Image YCbCrPositioning\": \"Centered\", \"Image ExifOffset\": \"102\", \"Thumbnail Compression\": \"JPEG (old-style)\", \"Thumbnail XResolution\": \"72\", \"Thumbnail YResolution\": \"72\", \"Thumbnail ResolutionUnit\": \"Pixels/Inch\", \"Thumbnail JPEGInterchangeFormat\": \"286\", \"Thumbnail JPEGInterchangeFormatLength\": \"8854\", \"EXIF ExifVersion\": \"\", \"EXIF ComponentsConfiguration\": \"\", \"EXIF FlashPixVersion\": \"\", \"EXIF ColorSpace\": \"sRGB\", \"EXIF ExifImageWidth\": \"4032\", \"EXIF ExifImageLength\": \"3024\", \"EXIF SceneCaptureType\": \"Standard\"}",
    "sha256": "f59653f5d24d92c881a5a9c10372c03de4ba81c09efed4f28f6c916c1c1a5aea"
}