{
    "url": "https://thumbs.dreamstime.com/t/%CE%B7-%CE%BA%CE%B1%CF%84%CE%BF%CF%87%CE%AE-%CE%B5%CE%BD%CF%8C%CF%82-%CF%80%CF%81%CE%B1%CE%B3%CE%BC%CE%B1%CF%84%CE%B9%CE%BA%CE%BF%CF%8D-%CF%80%CF%81%CE%BF%CF%83%CF%8E%CF%80%CE%BF%CF%85-%CE%B3%CE%B9%CE%B1-%CE%BC%CE%B9%CE%B1-%CF%80%CE%AD%CF%84%CF%81%CE%B1-%CE%B5%CE%AF%CE%BD%CE%B1%CE%B9-%CE%BA%CE%B1%CF%84%CE%B1%CF%80%CE%BB%CE%B7%CE%BA%CF%84%CE%B9%CE%BA%CE%AE-100433599.jpg",
    "key": "000023639",
    "status": "success",
    "error_message": null,
    "width": 512,
    "height": 512,
    "original_width": 284,
    "original_height": 160,
    "exif": "{}",
    "sha256": "77eff7949716faa3fcf96193aecda1d4872d6e9ac4f35b3b7219dc45421ee900"
}