{
    "url": "https://skalnispomeni.com/-cms/wp-content/uploads/2020/07/velikiyat-mongol-1400x788-75x75.jpg",
    "key": "000021051",
    "status": "success",
    "error_message": null,
    "width": 512,
    "height": 512,
    "original_width": 75,
    "original_height": 75,
    "exif": "{\"Image Orientation\": \"Horizontal (normal)\", \"Image XResolution\": \"120\", \"Image YResolution\": \"120\", \"Image ResolutionUnit\": \"Pixels/Inch\", \"Image Software\": \"ACDSee Pro 10\", \"Image DateTime\": \"2020:07:13 18:41:36\", \"Image YCbCrPositioning\": \"Centered\", \"Image ExifOffset\": \"160\", \"EXIF SubSecTime\": \"599\", \"EXIF ExifImageWidth\": \"1920\", \"EXIF ExifImageLength\": \"1080\"}",
    "sha256": "e2e8f4ef56a90030ce6c8ef0f4bc1ea0d9879e82818c7dba1e3446d1c0bee629"
}