{
    "url": "https://media.istockphoto.com/photos/skull-rock-formation-in-jerusalem-israel-picture-id638269090?k=6&amp;m=638269090&amp;s=612x612&amp;w=0&amp;h=cUiEjmkW75mvTOOZpjD8FIEYh61IMLk684wbc96Zq1Y=",
    "key": "000017856",
    "status": "success",
    "error_message": null,
    "width": 512,
    "height": 512,
    "original_width": 1024,
    "original_height": 683,
    "exif": "{\"Image ImageDescription\": \"Skull rock, possibly Golgotha, where Jesus Christ was crucified in Jerusalem, Israel\", \"Image Copyright\": \"JARAPhotos\"}",
    "sha256": "863fbcde2e2172797f7411050ce3c54881a4aff6fd05c9a8e9b8281b12ec07d2"
}