{
    "url": "https://i1.wp.com/0023am.net/wp-content/uploads/2016/08/himeji-faces.jpg?resize=640%2C458",
    "key": "000012944",
    "status": "success",
    "error_message": null,
    "width": 512,
    "height": 512,
    "original_width": 640,
    "original_height": 458,
    "exif": "{\"Image ImageWidth\": \"4000\", \"Image ImageLength\": \"2664\", \"Image BitsPerSample\": \"[8, 8, 8]\", \"Image PhotometricInterpretation\": \"2\", \"Image Make\": \"Canon\", \"Image Model\": \"Canon PowerShot S120\", \"Image Orientation\": \"Horizontal (normal)\", \"Image SamplesPerPixel\": \"3\", \"Image XResolution\": \"180\", \"Image YResolution\": \"180\", \"Image ResolutionUnit\": \"Pixels/Inch\", \"Image Software\": \"Adobe Photoshop CS5.1 Macintosh\", \"Image DateTime\": \"2016:08:21 13:35:37\", \"Image YCbCrPositioning\": \"Co-sited\", \"Image ExifOffset\": \"308\", \"GPS GPSVersionID\": \"[0, 0, 0, 0]\", \"Image GPSInfo\": \"1180\", \"Thumbnail Compression\": \"JPEG (old-style)\", \"Thumbnail XResolution\": \"72\", \"Thumbnail YResolution\": \"72\", \"Thumbnail ResolutionUnit\": \"Pixels/Inch\", \"Thumbnail JPEGInterchangeFormat\": \"1294\", \"Thumbnail JPEGInterchangeFormatLength\": \"3870\", \"EXIF ExposureTime\": \"1/30\", \"EXIF FNumber\": \"9/5\", \"EXIF ISOSpeedRatings\": \"320\", \"EXIF SensitivityType\": \"Standard Output Sensitivity and Recommended Exposure Index\", \"EXIF ExifVersion\": \"\", \"EXIF DateTimeOriginal\": \"2016:05:01 10:46:47\", \"EXIF DateTimeDigitized\": \"2016:05:01 10:46:47\", \"EXIF ComponentsConfiguration\": \"\", \"EXIF CompressedBitsPerPixel\": \"3\", \"EXIF ShutterSpeedValue\": \"157/32\", \"EXIF ApertureValue\": \"27/16\", \"EXIF ExposureBiasValue\": \"0\", \"EXIF MaxApertureValue\": \"27/16\", \"EXIF SubjectDistance\": \"199/100\", \"EXIF MeteringMode\": \"Pattern\", \"EXIF Flash\": \"Flash did not fire, compulsory flash mode\", \"EXIF FocalLength\": \"26/5\", \"EXIF FlashPixVersion\": \"\", \"EXIF ColorSpace\": \"sRGB\", \"EXIF ExifImageWidth\": \"640\", \"EXIF ExifImageLength\": \"458\", \"Interoperability InteroperabilityIndex\": \"R98\", \"Interoperability InteroperabilityVersion\": \"[0, 0, 0, 0]\", \"Interoperability RelatedImageWidth\": \"4000\", \"Interoperability RelatedImageLength\": \"2664\", \"EXIF InteroperabilityOffset\": \"1124\", \"EXIF FocalPlaneXResolution\": \"4000000/291\", \"EXIF FocalPlaneYResolution\": \"1000000/73\", \"EXIF FocalPlaneResolutionUnit\": \"2\", \"EXIF SensingMethod\": \"One-chip color area\", \"EXIF FileSource\": \"0\", \"EXIF CustomRendered\": \"Normal\", \"EXIF ExposureMode\": \"Auto Exposure\", \"EXIF WhiteBalance\": \"Auto\", \"EXIF DigitalZoomRatio\": \"1\", \"EXIF SceneCaptureType\": \"Standard\", \"EXIF CameraOwnerName\": \"\"}",
    "sha256": "cd500eebc07d408846f0b57f7af0e7917483885c0f7a2470de3e6083e7c403b7"
}