{
    "url": "https://arcticstardesign.com/wp-content/uploads/2020/01/pet124.jpg",
    "key": "000004859",
    "status": "success",
    "error_message": null,
    "width": 512,
    "height": 512,
    "original_width": 454,
    "original_height": 743,
    "exif": "{\"Image Artist\": \"David Ways\", \"Image ExifOffset\": \"2134\", \"Image XPAuthor\": \"\", \"Image Padding\": \"[]\", \"EXIF DateTimeOriginal\": \"2020:01:24 19:22:34\", \"EXIF DateTimeDigitized\": \"2020:01:24 19:22:34\", \"EXIF SubSecTimeOriginal\": \"66\", \"EXIF SubSecTimeDigitized\": \"66\", \"EXIF Padding\": \"[]\"}",
    "sha256": "9d80f577d422c92af8f6af2890691d58168fdbeae05a0d007596f2d0e3d9145a"
}