{
    "url": "https://cdn-ak.f.st-hatena.com/images/fotolife/a/aohige0718/20210411/20210411120100.jpg",
    "key": "000005764",
    "status": "success",
    "error_message": null,
    "width": 512,
    "height": 512,
    "original_width": 640,
    "original_height": 426,
    "exif": "{\"Image Software\": \"Syukukaku Ver28\", \"Image ExifOffset\": \"54\", \"EXIF ExifVersion\": \"\", \"EXIF DateTimeOriginal\": \"2021:04:10 14:35:34\", \"EXIF DateTimeDigitized\": \"2021:04:10 14:35:34\"}",
    "sha256": "0781c1608a691514e33546b2db054901bad7a417de8c0e3d37935e95da80711d"
}